e_drone/__init__.py
e_drone/__main__.py
e_drone/crc.py
e_drone/drone.py
e_drone/protocol.py
e_drone/receiver.py
e_drone/storage.py
e_drone/system.py
e_drone/tools/__init__.py
e_drone/tools/parser.py
e_drone/tools/update.py
e_drone-22.6.2.dist-info/LICENSE
e_drone-22.6.2.dist-info/METADATA
e_drone-22.6.2.dist-info/WHEEL
e_drone-22.6.2.dist-info/top_level.txt
e_drone-22.6.2.dist-info/RECORD
