Metadata-Version: 2.1
Name: e-drone
Version: 22.6.2
Summary: Library for BYROBOT Drones.
Home-page: http://www.byrobot.co.kr
Author: BYROBOT
Author-email: dev@byrobot.co.kr
License: UNKNOWN
Platform: UNKNOWN
License-File: LICENSE
Requires-Dist: pyserial (>=3.4)
Requires-Dist: colorama (>=0.4.0)
